.gitignore
LICENSE.md
MANIFEST.in
README.md
requirements.txt
setup.py
assets/usage.png
pgls/__init__.py
pgls.egg-info/PKG-INFO
pgls.egg-info/SOURCES.txt
pgls.egg-info/dependency_links.txt
pgls.egg-info/entry_points.txt
pgls.egg-info/requires.txt
pgls.egg-info/top_level.txt