Metadata-Version: 2.1
Name: pgls
Version: 1.0.1
Summary: CLI utility to display postgres database information as a tree.
Home-page: https://github.com/codingjerk/pgls
Author: Denis Gruzdev
Author-email: codingjerk@gmail.com
License: MIT
Platform: UNKNOWN
